matgen/__init__.py
matgen/base.py
matgen/characterise.py
matgen/entropic.py
matgen/matutils.py
matgen/ndisangles.py
matgen/ndisorientquat.py
matgen/sparsemat.py
matgen/utils.py
tests/__init__.py
tests/test_base.py
tests/test_sparsemat.py
PCCanalyser-0.6.0.dist-info/LICENSE
PCCanalyser-0.6.0.dist-info/METADATA
PCCanalyser-0.6.0.dist-info/WHEEL
PCCanalyser-0.6.0.dist-info/entry_points.txt
PCCanalyser-0.6.0.dist-info/top_level.txt
PCCanalyser-0.6.0.dist-info/RECORD
