Metadata-Version: 2.1
Name: PCCanalyser
Version: 0.6.0
Summary: Polyhedral Cell Complex (PCC) Analysis tools
Author: Oleg Bushuev
Project-URL: documentation, https://github.com/PRISBteam/Voronoi_PCC_Analyser
Project-URL: repository, https://github.com/PRISBteam/Voronoi_PCC_Analyser.git
License-File: LICENSE
Requires-Dist: numpy >=1.21.5
Requires-Dist: scipy >=1.7.3
Requires-Dist: tqdm >=4.64.1
Requires-Dist: jupyterlab >=3.4.4
Requires-Dist: matplotlib >=3.5.2
Requires-Dist: pandas >=1.3.4
